xtr_warp/__init__.py
xtr_warp/evaluation.py
xtr_warp/search.py
xtr_warp/xtr_warp_rs.cpython-312-x86_64-linux-gnu.so
xtr_warp_rs.libs/libc10-7a772df9.so
xtr_warp_rs-0.0.2.290.dist-info/METADATA
xtr_warp_rs-0.0.2.290.dist-info/WHEEL
xtr_warp_rs-0.0.2.290.dist-info/RECORD
xtr_warp_rs-0.0.2.290.dist-info/licenses/LICENSE
