Metadata-Version: 2.4
Name: xtr-warp-rs
Version: 0.0.2.290
Classifier: Programming Language :: Python :: 3
Classifier: Programming Language :: Rust
Classifier: Operating System :: OS Independent
Requires-Dist: fastkmeans>=0.5.0
Requires-Dist: joblib>=1.5.1
Requires-Dist: torch>=2.9,<2.10
Requires-Dist: maturin>=1.8.6
Requires-Dist: numpy>=1.26.4
Requires-Dist: setuptools>=78.1.1
Requires-Dist: maturin>=1.8.6 ; extra == 'dev'
Requires-Dist: pytest-cov>=5.0.0 ; extra == 'dev'
Requires-Dist: pytest>=7.4.4 ; extra == 'dev'
Requires-Dist: ruff>=0.1.15 ; extra == 'dev'
Requires-Dist: pre-commit>=3.0.0 ; extra == 'dev'
Requires-Dist: beir>=2.1.0 ; extra == 'dev'
Requires-Dist: ranx>=0.3.20 ; extra == 'dev'
Provides-Extra: dev
License-File: LICENSE
Summary: XTR-Warp
Keywords: 
Author-email: Pau Montserrat <pau.mopuig@gmail.com>
Requires-Python: >=3.10
Project-URL: Documentation, https://github.com/pau-mensa/xtr-warp-rs
Project-URL: Homepage, https://github.com/pau-mensa/xtr-warp-rs
Project-URL: Repository, https://github.com/pau-mensa/xtr-warp-rs
